<?xml version="1.0" encoding="ISO-8859-1"?>
<ponude>



<ponuda><id>1</id><naziv>Venecija</naziv><opis>Predivno putovanje</opis><detaljanOpis>5 dana u prelijepoj Italiji</detaljanOpis><slika>ponuda1.jpg</slika><cijena>123</cijena></ponuda>
<ponuda><id>2</id><naziv>London</naziv><opis>Predivno putovanje</opis><detaljanOpis>4 dana u prelijepoj Engleskoj</detaljanOpis><slika>London.jpg</slika><cijena>400</cijena></ponuda>
<ponuda><id>3</id><naziv>Berlin</naziv><opis>Predivno putovanje</opis><detaljanOpis>5 dana u prelijepoj Njemackoj</detaljanOpis><slika>berlin1.jpg</slika><cijena>350</cijena></ponuda>
<ponuda><id>4</id><naziv>Amsterdam</naziv><opis>Studentski pohod</opis><detaljanOpis>5 dana dobrog provoda</detaljanOpis><slika>amsterdam1.jpg</slika><cijena>350</cijena></ponuda>
</ponude>
